cities_coordinates/__init__.py
cities_coordinates/cities_coordinates.py
cities_coordinates-0.1.data/scripts/__init__.py
cities_coordinates-0.1.dist-info/LICENCE
cities_coordinates-0.1.dist-info/METADATA
cities_coordinates-0.1.dist-info/WHEEL
cities_coordinates-0.1.dist-info/top_level.txt
cities_coordinates-0.1.dist-info/RECORD
