Metadata-Version: 2.1
Name: cities-coordinates
Version: 0.1
Summary: A city coordinator package. The goal behind this package is to map cities arround the world with their coordinations without any need for an internet connection
Home-page: https://github.com/sofzer/cities_coordinates
Author: Sofiene  Memmi
Author-email: sofiene.memmi@gmail.com
License: UNKNOWN
Download-URL: https://github.com/user/reponame/archive/v_01.tar.gz
Platform: UNKNOWN
Classifier: Programming Language :: Python :: 3
Classifier: License :: OSI Approved :: MIT License
Classifier: Operating System :: OS Independent
